tree_sitter_toon/__init__.py
tree_sitter_toon/__init__.pyi
tree_sitter_toon/_binding.pyd
tree_sitter_toon/binding.c
tree_sitter_toon/py.typed
tree_sitter_toon-0.0.10.dist-info/LICENSE
tree_sitter_toon-0.0.10.dist-info/METADATA
tree_sitter_toon-0.0.10.dist-info/WHEEL
tree_sitter_toon-0.0.10.dist-info/top_level.txt
tree_sitter_toon-0.0.10.dist-info/RECORD
