Metadata-Version: 2.1
Name: tree-sitter-toon
Version: 0.0.10
Summary: TOON (Token-Oriented Object Notation) grammar for tree-sitter
Author-email: 3swordman <yyuxiaoran@qq.com>
License: GPL-3.0-or-later
Project-URL: Homepage, https://github.com/3swordman/tree-sitter-toon
Project-URL: Repository, https://github.com/3swordman/tree-sitter-toon
Project-URL: Issues, https://github.com/3swordman/tree-sitter-toon/issues
Project-URL: Changelog, https://github.com/3swordman/tree-sitter-toon/releases
Keywords: incremental,parsing,tree-sitter,toon,serialization,data-format
Classifier: Development Status :: 4 - Beta
Classifier: Intended Audience :: Developers
Classifier: License :: OSI Approved :: GNU General Public License v3 or later (GPLv3+)
Classifier: Programming Language :: C
Classifier: Programming Language :: Python :: 3
Classifier: Programming Language :: Python :: 3.10
Classifier: Programming Language :: Python :: 3.11
Classifier: Programming Language :: Python :: 3.12
Classifier: Programming Language :: Python :: Implementation :: CPython
Classifier: Topic :: Software Development :: Compilers
Classifier: Topic :: Software Development :: Libraries :: Python Modules
Classifier: Topic :: Text Processing :: Linguistic
Classifier: Typing :: Typed
Requires-Python: >=3.10
License-File: LICENSE
Provides-Extra: core
Requires-Dist: tree-sitter ~=0.24 ; extra == 'core'
